AUTHORS.rst
CONTRIBUTING.rst
HISTORY.rst
LICENSE
MANIFEST.in
README.rst
setup.cfg
setup.py
djangocms_spa_vue_js/__init__.py
djangocms_spa_vue_js/cms_menus.py
djangocms_spa_vue_js/menu_helpers.py
djangocms_spa_vue_js/middleware.py
djangocms_spa_vue_js/models.py
djangocms_spa_vue_js/router_helpers.py
djangocms_spa_vue_js/views.py
djangocms_spa_vue_js.egg-info/PKG-INFO
djangocms_spa_vue_js.egg-info/SOURCES.txt
djangocms_spa_vue_js.egg-info/dependency_links.txt
djangocms_spa_vue_js.egg-info/not-zip-safe
djangocms_spa_vue_js.egg-info/requires.txt
djangocms_spa_vue_js.egg-info/top_level.txt
djangocms_spa_vue_js/templatetags/__init__.py
djangocms_spa_vue_js/templatetags/router_tags.py