Metadata-Version: 1.1
Name: djangocms-spa-vue-js
Version: 0.1.24
Summary: This package prepares your django CMS and vue.js project to create a single-page application (SPA).
Home-page: https://github.com/dreipol/djangocms-spa-vue-js
Author: dreipol GmbH
Author-email: dev@dreipol.ch
License: MIT
Keywords: djangocms-spa-vue-js
Platform: UNKNOWN
Classifier: Development Status :: 3 - Alpha
Classifier: Framework :: Django
Classifier: Framework :: Django :: 1.8
Classifier: Framework :: Django :: 1.9
Classifier: Framework :: Django :: 1.10
Classifier: Intended Audience :: Developers
Classifier: License :: OSI Approved :: BSD License
Classifier: Natural Language :: English
Classifier: Programming Language :: Python :: 2
Classifier: Programming Language :: Python :: 2.7
Classifier: Programming Language :: Python :: 3
Classifier: Programming Language :: Python :: 3.3
Classifier: Programming Language :: Python :: 3.4
Classifier: Programming Language :: Python :: 3.5
